{
	"env": 3000,
	"subject": "3000",
	"line_num": 0,
	"first": {
		"dev_index": "1",
		"dev_info": "etc",
		"width": 483,
		"height": 368.1345029239766,
		"timestamp": 1565830736425,
		"lines": [
			[
				138.5,
				30.5,
				0
			],
			[
				140.5,
				30.5,
				78
			],
			[
				142.5,
				31.5,
				91
			],
			[
				145,
				32.5,
				103
			],
			[
				152,
				35,
				121
			],
			[
				156,
				36.5,
				136
			],
			[
				164,
				39,
				154
			],
			[
				167.5,
				40.5,
				170
			],
			[
				175,
				43,
				186
			],
			[
				181.5,
				45,
				204
			],
			[
				187,
				47,
				219
			],
			[
				190,
				48,
				238
			],
			[
				196.5,
				50,
				253
			],
			[
				200,
				51,
				269
			],
			[
				206.5,
				53,
				286
			],
			[
				213,
				54.5,
				304
			],
			[
				219,
				56.5,
				319
			],
			[
				222,
				57.5,
				336
			],
			[
				230,
				59.5,
				353
			],
			[
				233.5,
				60.5,
				369
			],
			[
				240,
				62,
				386
			],
			[
				246,
				63.5,
				403
			],
			[
				251.5,
				65,
				421
			],
			[
				254,
				66,
				436
			],
			[
				259.5,
				68,
				454
			],
			[
				266,
				69,
				471
			],
			[
				269,
				70,
				486
			],
			[
				275,
				71.5,
				503
			],
			[
				280,
				72.5,
				520
			],
			[
				282.5,
				73,
				538
			],
			[
				288.5,
				74.5,
				553
			],
			[
				294,
				75.5,
				571
			],
			[
				296.5,
				76.5,
				588
			],
			[
				301,
				78,
				604
			],
			[
				305.5,
				80,
				619
			],
			[
				307.5,
				81,
				637
			],
			[
				313,
				83,
				654
			],
			[
				315,
				84,
				669
			],
			[
				319.5,
				85.5,
				686
			],
			[
				324,
				87,
				704
			],
			[
				329,
				89,
				721
			],
			[
				331.5,
				90,
				736
			],
			[
				336.5,
				92,
				754
			],
			[
				340,
				93,
				771
			],
			[
				342,
				93.5,
				786
			],
			[
				345,
				94.5,
				804
			],
			[
				348.5,
				96.5,
				820
			],
			[
				352,
				98.5,
				838
			],
			[
				354,
				99.5,
				854
			],
			[
				355.5,
				100.5,
				870
			],
			[
				358.5,
				101.5,
				888
			],
			[
				360.5,
				103,
				905
			],
			[
				362.5,
				104,
				920
			],
			[
				364,
				105.5,
				938
			],
			[
				365,
				106,
				954
			],
			[
				367,
				107,
				971
			],
			[
				368.5,
				107.5,
				988
			],
			[
				371.5,
				109,
				1004
			],
			[
				375,
				110.5,
				1021
			],
			[
				376.5,
				111.5,
				1036
			],
			[
				380.5,
				113,
				1053
			],
			[
				384,
				114.5,
				1070
			],
			[
				386,
				115,
				1086
			],
			[
				390,
				117.5,
				1103
			],
			[
				394.5,
				119,
				1120
			],
			[
				396.5,
				120,
				1137
			],
			[
				400.5,
				121.5,
				1153
			],
			[
				403.5,
				123,
				1171
			],
			[
				405,
				124,
				1188
			],
			[
				408.5,
				125.5,
				1205
			],
			[
				412,
				127.5,
				1221
			],
			[
				417,
				129.5,
				1238
			],
			[
				419,
				130,
				1254
			],
			[
				423.5,
				131.5,
				1270
			],
			[
				426,
				132,
				1287
			],
			[
				430.5,
				133,
				1304
			]
		]
	},
	"second": {
		"dev_index": "2",
		"dev_info": "etc",
		"width": 483,
		"height": 553.476653696498,
		"timestamp": 1565830738225,
		"lines": [
			[
				82,
				48.5,
				0
			],
			[
				84,
				48.5,
				21
			],
			[
				89,
				50,
				38
			],
			[
				92,
				51.5,
				56
			],
			[
				97,
				54.5,
				73
			],
			[
				100,
				56,
				88
			],
			[
				104.5,
				58,
				106
			],
			[
				109.5,
				60,
				123
			],
			[
				115,
				62,
				138
			],
			[
				117.5,
				62.5,
				155
			],
			[
				121,
				64,
				172
			],
			[
				122.5,
				65,
				189
			],
			[
				126,
				67,
				205
			],
			[
				130,
				69.5,
				222
			],
			[
				135,
				72.5,
				240
			],
			[
				137,
				73.5,
				254
			],
			[
				140,
				76,
				273
			],
			[
				143.5,
				78,
				290
			],
			[
				145,
				79,
				305
			],
			[
				149,
				80.5,
				321
			],
			[
				152.5,
				82,
				340
			],
			[
				154,
				82,
				355
			],
			[
				157.5,
				83,
				372
			],
			[
				159,
				83.5,
				388
			],
			[
				163,
				84.5,
				406
			],
			[
				166,
				86,
				423
			],
			[
				170,
				87.5,
				438
			],
			[
				172,
				88.5,
				456
			],
			[
				176.5,
				90,
				473
			],
			[
				180.5,
				92,
				490
			],
			[
				182,
				92.5,
				505
			],
			[
				184.5,
				93.5,
				522
			],
			[
				186.5,
				95,
				540
			],
			[
				187.5,
				95.5,
				555
			],
			[
				190,
				97,
				572
			],
			[
				191.5,
				97.5,
				589
			],
			[
				195,
				99.5,
				607
			],
			[
				199,
				101.5,
				623
			],
			[
				203,
				103.5,
				640
			],
			[
				204.5,
				104,
				657
			],
			[
				207,
				106,
				671
			],
			[
				208.5,
				106.5,
				688
			],
			[
				211,
				108,
				706
			],
			[
				213,
				109,
				723
			],
			[
				215,
				110,
				738
			],
			[
				216,
				110.5,
				755
			],
			[
				219,
				112.5,
				772
			],
			[
				222,
				113.5,
				789
			],
			[
				223.5,
				114,
				805
			],
			[
				225,
				115,
				822
			],
			[
				226,
				115.5,
				840
			],
			[
				227,
				116,
				855
			],
			[
				228.5,
				116.5,
				873
			],
			[
				230,
				117,
				889
			],
			[
				231,
				117.5,
				907
			],
			[
				232.5,
				118.5,
				922
			],
			[
				234,
				119.5,
				940
			],
			[
				235.5,
				119.5,
				957
			],
			[
				236.5,
				120,
				973
			],
			[
				237.5,
				121,
				989
			],
			[
				238.5,
				121.5,
				1006
			],
			[
				240,
				122.5,
				1024
			],
			[
				241,
				124,
				1039
			]
		]
	}
}