{
	"env": 4000,
	"subject": "4000",
	"line_num": 0,
	"first": {
		"dev_index": "1",
		"dev_info": "etc",
		"width": 483,
		"height": 368.1345029239766,
		"timestamp": 1565831403131,
		"lines": [
			[
				45.5,
				149,
				0
			],
			[
				45,
				148,
				3
			],
			[
				47.5,
				148,
				58
			],
			[
				52,
				148.5,
				73
			],
			[
				54.5,
				148,
				90
			],
			[
				59.5,
				147.5,
				107
			],
			[
				64,
				147.5,
				124
			],
			[
				65.5,
				147,
				141
			],
			[
				69,
				146.5,
				158
			],
			[
				71.5,
				145.5,
				173
			],
			[
				73,
				145,
				190
			],
			[
				75.5,
				145,
				207
			],
			[
				77,
				144.5,
				224
			],
			[
				80.5,
				144.5,
				240
			],
			[
				84.5,
				144,
				257
			],
			[
				88.5,
				143.5,
				274
			],
			[
				92,
				143.5,
				290
			],
			[
				94,
				143.5,
				307
			],
			[
				97,
				142.5,
				323
			],
			[
				98.5,
				142.5,
				341
			],
			[
				101.5,
				141.5,
				356
			],
			[
				104.5,
				141,
				374
			],
			[
				108,
				140,
				391
			],
			[
				110.5,
				139,
				408
			],
			[
				115.5,
				138.5,
				424
			],
			[
				117.5,
				138.5,
				441
			],
			[
				122,
				137.5,
				457
			],
			[
				126,
				137,
				475
			],
			[
				131,
				136,
				491
			],
			[
				134,
				135.5,
				507
			],
			[
				139.5,
				134,
				524
			],
			[
				142.5,
				133,
				541
			],
			[
				148,
				132,
				556
			],
			[
				153,
				130,
				574
			],
			[
				158,
				129,
				591
			],
			[
				160.5,
				128.5,
				608
			],
			[
				165,
				127.5,
				624
			],
			[
				167,
				127.5,
				642
			],
			[
				171.5,
				126.5,
				659
			],
			[
				176.5,
				125.5,
				674
			],
			[
				180.5,
				125,
				691
			],
			[
				182.5,
				124.5,
				708
			],
			[
				186.5,
				123.5,
				724
			],
			[
				188,
				123,
				740
			],
			[
				192,
				121,
				758
			],
			[
				197,
				120,
				775
			],
			[
				201,
				118.5,
				791
			],
			[
				203.5,
				118,
				807
			],
			[
				209,
				116.5,
				825
			],
			[
				212,
				116,
				842
			],
			[
				218.5,
				114,
				858
			],
			[
				225.5,
				112.5,
				875
			],
			[
				233,
				111,
				891
			],
			[
				236,
				110.5,
				908
			],
			[
				243.5,
				109.5,
				924
			],
			[
				247,
				109,
				942
			],
			[
				253,
				108,
				959
			],
			[
				259.5,
				107,
				974
			],
			[
				266.5,
				106,
				990
			],
			[
				269,
				106,
				1009
			],
			[
				274,
				105,
				1025
			],
			[
				276,
				104.5,
				1041
			],
			[
				282.5,
				103.5,
				1058
			],
			[
				288.5,
				102.5,
				1075
			],
			[
				295.5,
				101,
				1091
			],
			[
				298.5,
				100,
				1108
			],
			[
				304.5,
				98.5,
				1124
			],
			[
				307.5,
				97.5,
				1142
			],
			[
				313.5,
				96.5,
				1158
			],
			[
				318,
				94.5,
				1175
			],
			[
				323,
				94,
				1191
			],
			[
				325,
				94.5,
				1207
			],
			[
				327.5,
				95,
				1225
			],
			[
				328.5,
				95,
				1242
			],
			[
				329.5,
				95,
				1258
			],
			[
				331,
				95.5,
				1275
			],
			[
				334.5,
				95.5,
				1291
			],
			[
				336.5,
				95,
				1309
			],
			[
				342.5,
				94.5,
				1325
			]
		]
	},
	"second": {
		"dev_index": "2",
		"dev_info": "etc",
		"width": 483,
		"height": 552.5369649805448,
		"timestamp": 1565831405759,
		"lines": [
			[
				221,
				137.5,
				0
			],
			[
				221.5,
				137.5,
				17
			],
			[
				225,
				135.5,
				35
			],
			[
				227,
				135.5,
				47
			],
			[
				233,
				134.5,
				64
			],
			[
				239.5,
				133,
				81
			],
			[
				242.5,
				132.5,
				97
			],
			[
				247.5,
				132,
				113
			],
			[
				249.5,
				131.5,
				131
			],
			[
				253.5,
				131.5,
				147
			],
			[
				257,
				131.5,
				165
			],
			[
				260,
				131.5,
				181
			],
			[
				262,
				131,
				197
			],
			[
				266,
				131,
				214
			],
			[
				267.5,
				130.5,
				230
			],
			[
				270.5,
				130,
				247
			],
			[
				273.5,
				129.5,
				266
			],
			[
				276.5,
				129,
				280
			],
			[
				279,
				129,
				298
			],
			[
				284.5,
				127.5,
				316
			],
			[
				288,
				126.5,
				331
			],
			[
				297.5,
				124.5,
				347
			],
			[
				306.5,
				123,
				365
			],
			[
				310,
				122,
				381
			],
			[
				315,
				121,
				398
			],
			[
				318.5,
				121,
				415
			],
			[
				320,
				121,
				431
			],
			[
				324.5,
				121,
				448
			],
			[
				329.5,
				120.5,
				465
			],
			[
				334.5,
				120.5,
				482
			],
			[
				337.5,
				120,
				498
			],
			[
				343.5,
				119.5,
				515
			],
			[
				348.5,
				118.5,
				531
			],
			[
				350.5,
				118.5,
				548
			],
			[
				353,
				117.5,
				564
			],
			[
				355.5,
				116.5,
				580
			],
			[
				357,
				116.5,
				598
			],
			[
				361.5,
				114.5,
				615
			],
			[
				363.5,
				114,
				631
			],
			[
				368,
				112.5,
				647
			],
			[
				372,
				111.5,
				664
			],
			[
				375.5,
				110,
				682
			],
			[
				377,
				110,
				698
			],
			[
				380,
				109.5,
				715
			],
			[
				381,
				109.5,
				731
			],
			[
				385,
				109.5,
				748
			],
			[
				390,
				108.5,
				765
			],
			[
				396,
				107.5,
				782
			],
			[
				402,
				106.5,
				799
			],
			[
				405,
				106,
				815
			],
			[
				408.5,
				105.5,
				832
			],
			[
				409.5,
				105,
				849
			],
			[
				411,
				105,
				865
			],
			[
				414.5,
				104.5,
				882
			],
			[
				417,
				104,
				899
			],
			[
				422,
				103,
				916
			],
			[
				424.5,
				102.5,
				931
			],
			[
				429.5,
				102.5,
				947
			],
			[
				433,
				102.5,
				965
			],
			[
				435,
				102.5,
				981
			],
			[
				436,
				102.5,
				998
			],
			[
				437,
				102,
				1014
			],
			[
				437.5,
				102,
				1033
			],
			[
				437.5,
				101.5,
				1058
			],
			[
				437.5,
				101,
				1098
			],
			[
				440.5,
				100.5,
				1115
			],
			[
				444.5,
				100,
				1131
			],
			[
				447,
				99,
				1148
			]
		]
	}
}